[{"web-scraper-order": "\ufeffweb-scraper-order", "web-scraper-start-url": "web-scraper-start-url", "url_link": "url", "url-href": "url-href"},{"web-scraper-order": "1638891898-607", "web-scraper-start-url": "https://fr.kompass.com/r/ile-de-france/fr_11/", "url_link": "", "url-href": "https://www.incore.fr/"},{"web-scraper-order": "1638891898-619", "web-scraper-start-url": "https://fr.kompass.com/r/ile-de-france/fr_11/", "url_link": "", "url-href": "https://www.etanco.eu/fr/fr/index-f.aspx"},{"web-scraper-order": "1638891898-578", "web-scraper-start-url": "https://fr.kompass.com/r/ile-de-france/fr_11/", "url_link": "", "url-href": "https://www.ericsalmon.com/"},{"web-scraper-order": "1638891898-598", "web-scraper-start-url": "https://fr.kompass.com/r/ile-de-france/fr_11/", "url_link": "", "url-href": "https://www.3d-plus.com/"},{"web-scraper-order": "1638891898-618", "web-scraper-start-url": "https://fr.kompass.com/r/ile-de-france/fr_11/", "url_link": "", "url-href": "http://www.2sdti.com/"},{"web-scraper-order": "1638891898-564", "web-scraper-start-url": "https://fr.kompass.com/r/ile-de-france/fr_11/", "url_link": "", "url-href": "https://globalfilter.com/fr/"},{"web-scraper-order": "1638891898-585", "web-scraper-start-url": "https://fr.kompass.com/r/ile-de-france/fr_11/", "url_link": "", "url-href": "https://meteofrance.com/"},{"web-scraper-order": "1638891898-612", "web-scraper-start-url": "https://fr.kompass.com/r/ile-de-france/fr_11/", "url_link": "", "url-href": "http://www.yaki.com/"},{"web-scraper-order": "1638891898-577", "web-scraper-start-url": "https://fr.kompass.com/r/ile-de-france/fr_11/", "url_link": "", "url-href": "https://www.edimeta.fr/"},{"web-scraper-order": "1638891898-621", "web-scraper-start-url": "https://fr.kompass.com/r/ile-de-france/fr_11/", "url_link": "", "url-href": "https://www.bewell-connect.com/"},{"web-scraper-order": "1638891898-566", "web-scraper-start-url": "https://fr.kompass.com/r/ile-de-france/fr_11/", "url_link": "", "url-href": "https://www.groupefsc.com/"},{"web-scraper-order": "1638891898-590", "web-scraper-start-url": "https://fr.kompass.com/r/ile-de-france/fr_11/", "url_link": "", "url-href": "https://a2fconseils.fr/"},{"web-scraper-order": "1638891898-581", "web-scraper-start-url": "https://fr.kompass.com/r/ile-de-france/fr_11/", "url_link": "", "url-href": "https://www.fisa.com/"},{"web-scraper-order": "1638891898-623", "web-scraper-start-url": "https://fr.kompass.com/r/ile-de-france/fr_11/", "url_link": "", "url-href": "https://www.chantalbaudron.fr/"},{"web-scraper-order": "1638891898-631", "web-scraper-start-url": "https://fr.kompass.com/r/ile-de-france/fr_11/", "url_link": "", "url-href": "https://easylog.fr/"},{"web-scraper-order": "1638891898-594", "web-scraper-start-url": "https://fr.kompass.com/r/ile-de-france/fr_11/", "url_link": "", "url-href": "http://www.thaiembassy.fr/fr"},{"web-scraper-order": "1638891898-609", "web-scraper-start-url": "https://fr.kompass.com/r/ile-de-france/fr_11/", "url_link": "", "url-href": "https://www.heller.biz/"},{"web-scraper-order": "1638891898-573", "web-scraper-start-url": "https://fr.kompass.com/r/ile-de-france/fr_11/", "url_link": "", "url-href": "https://pouchard.fr/"},{"web-scraper-order": "1638891898-579", "web-scraper-start-url": "https://fr.kompass.com/r/ile-de-france/fr_11/", "url_link": "", "url-href": "http://paris.itamaraty.gov.br/fr"},{"web-scraper-order": "1638891898-616", "web-scraper-start-url": "https://fr.kompass.com/r/ile-de-france/fr_11/", "url_link": "", "url-href": "https://metropolitan-influence.com/"},{"web-scraper-order": "1638891898-600", "web-scraper-start-url": "https://fr.kompass.com/r/ile-de-france/fr_11/", "url_link": "", "url-href": "https://www.hubone.fr/"},{"web-scraper-order": "1638891898-560", "web-scraper-start-url": "https://fr.kompass.com/r/ile-de-france/fr_11/", "url_link": "", "url-href": "http://www.xrite.com/"},{"web-scraper-order": "1638891898-626", "web-scraper-start-url": "https://fr.kompass.com/r/ile-de-france/fr_11/", "url_link": "", "url-href": "https://chocolateriejanin.com/"},{"web-scraper-order": "1638891898-596", "web-scraper-start-url": "https://fr.kompass.com/r/ile-de-france/fr_11/", "url_link": "", "url-href": "https://enjeux-dirigeants.com/"},{"web-scraper-order": "1638891898-634", "web-scraper-start-url": "https://fr.kompass.com/r/ile-de-france/fr_11/", "url_link": "", "url-href": "https://www.cnam.fr/"},{"web-scraper-order": "1638891898-603", "web-scraper-start-url": "https://fr.kompass.com/r/ile-de-france/fr_11/", "url_link": "", "url-href": "https://www.valdemarne.fr/"},{"web-scraper-order": "1638891898-611", "web-scraper-start-url": "https://fr.kompass.com/r/ile-de-france/fr_11/", "url_link": "", "url-href": "https://agora-technique.com/"},{"web-scraper-order": "1638891898-630", "web-scraper-start-url": "https://fr.kompass.com/r/ile-de-france/fr_11/", "url_link": "", "url-href": "https://altik.com/"},{"web-scraper-order": "1638891898-595", "web-scraper-start-url": "https://fr.kompass.com/r/ile-de-france/fr_11/", "url_link": "", "url-href": "https://igienair.com/"},{"web-scraper-order": "1638891898-624", "web-scraper-start-url": "https://fr.kompass.com/r/ile-de-france/fr_11/", "url_link": "", "url-href": "https://eda.admin.ch/paris"},{"web-scraper-order": "1638891898-592", "web-scraper-start-url": "https://fr.kompass.com/r/ile-de-france/fr_11/", "url_link": "", "url-href": "https://www.univarsolutions.com/fr/"},{"web-scraper-order": "1638891898-586", "web-scraper-start-url": "https://fr.kompass.com/r/ile-de-france/fr_11/", "url_link": "", "url-href": "http://www.la-sofia.org/"},{"web-scraper-order": "1638891898-572", "web-scraper-start-url": "https://fr.kompass.com/r/ile-de-france/fr_11/", "url_link": "", "url-href": "https://www.caprari.com/"},{"web-scraper-order": "1638891898-613", "web-scraper-start-url": "https://fr.kompass.com/r/ile-de-france/fr_11/", "url_link": "", "url-href": "http://www.aubryntv.com/"},{"web-scraper-order": "1638891898-615", "web-scraper-start-url": "https://fr.kompass.com/r/ile-de-france/fr_11/", "url_link": "", "url-href": "https://www.kellyservices.fr/"},{"web-scraper-order": "1638891898-606", "web-scraper-start-url": "https://fr.kompass.com/r/ile-de-france/fr_11/", "url_link": "", "url-href": "https://www.actemium-ndt-pes.com/"},{"web-scraper-order": "1638891898-567", "web-scraper-start-url": "https://fr.kompass.com/r/ile-de-france/fr_11/", "url_link": "", "url-href": "https://advens-france.com/"},{"web-scraper-order": "1638891898-627", "web-scraper-start-url": "https://fr.kompass.com/r/ile-de-france/fr_11/", "url_link": "", "url-href": "https://www.siemens.fr/finance"},{"web-scraper-order": "1638891898-576", "web-scraper-start-url": "https://fr.kompass.com/r/ile-de-france/fr_11/", "url_link": "", "url-href": "https://www.pall.com/"},{"web-scraper-order": "1638891898-617", "web-scraper-start-url": "https://fr.kompass.com/r/ile-de-france/fr_11/", "url_link": "", "url-href": "https://www.messer.fr/"},{"web-scraper-order": "1638891898-587", "web-scraper-start-url": "https://fr.kompass.com/r/ile-de-france/fr_11/", "url_link": "", "url-href": "https://www.nfon.com/fr/"},{"web-scraper-order": "1638891898-629", "web-scraper-start-url": "https://fr.kompass.com/r/ile-de-france/fr_11/", "url_link": "", "url-href": "https://dbao-group.com/"},{"web-scraper-order": "1638891898-559", "web-scraper-start-url": "https://fr.kompass.com/r/ile-de-france/fr_11/", "url_link": "", "url-href": "https://logfret.com/"},{"web-scraper-order": "1638891898-568", "web-scraper-start-url": "https://fr.kompass.com/r/ile-de-france/fr_11/", "url_link": "", "url-href": "http://www.societex.fr/"},{"web-scraper-order": "1638891898-604", "web-scraper-start-url": "https://fr.kompass.com/r/ile-de-france/fr_11/", "url_link": "", "url-href": "http://www.gefi.net/"},{"web-scraper-order": "1638891898-608", "web-scraper-start-url": "https://fr.kompass.com/r/ile-de-france/fr_11/", "url_link": "", "url-href": "https://tecadis-systems.com/"},{"web-scraper-order": "1638891898-570", "web-scraper-start-url": "https://fr.kompass.com/r/ile-de-france/fr_11/", "url_link": "", "url-href": "http://www.data4group.com/"},{"web-scraper-order": "1638891898-632", "web-scraper-start-url": "https://fr.kompass.com/r/ile-de-france/fr_11/", "url_link": "", "url-href": "https://www.fibox.fr/"},{"web-scraper-order": "1638891898-571", "web-scraper-start-url": "https://fr.kompass.com/r/ile-de-france/fr_11/", "url_link": "", "url-href": "https://astronova.fr/"},{"web-scraper-order": "1638891898-599", "web-scraper-start-url": "https://fr.kompass.com/r/ile-de-france/fr_11/", "url_link": "", "url-href": "https://transport-fde.com/"},{"web-scraper-order": "1638891898-597", "web-scraper-start-url": "https://fr.kompass.com/r/ile-de-france/fr_11/", "url_link": "", "url-href": "https://del.fr/"},{"web-scraper-order": "1638891898-602", "web-scraper-start-url": "https://fr.kompass.com/r/ile-de-france/fr_11/", "url_link": "", "url-href": "https://www.h2k.fr/"},{"web-scraper-order": "1638891898-605", "web-scraper-start-url": "https://fr.kompass.com/r/ile-de-france/fr_11/", "url_link": "", "url-href": "https://placedubonheur.com/"},{"web-scraper-order": "1638891898-591", "web-scraper-start-url": "https://fr.kompass.com/r/ile-de-france/fr_11/", "url_link": "", "url-href": "https://www.sodexo.fr/"},{"web-scraper-order": "1638891898-575", "web-scraper-start-url": "https://fr.kompass.com/r/ile-de-france/fr_11/", "url_link": "", "url-href": "http://www.kompass.com/"},{"web-scraper-order": "1638891898-580", "web-scraper-start-url": "https://fr.kompass.com/r/ile-de-france/fr_11/", "url_link": "", "url-href": "https://www.mecalectro.com/"},{"web-scraper-order": "1638891898-584", "web-scraper-start-url": "https://fr.kompass.com/r/ile-de-france/fr_11/", "url_link": "", "url-href": "https://mapa-assurances.fr/"},{"web-scraper-order": "1638891898-582", "web-scraper-start-url": "https://fr.kompass.com/r/ile-de-france/fr_11/", "url_link": "", "url-href": "https://iguanesolutions.com/"},{"web-scraper-order": "1638891898-622", "web-scraper-start-url": "https://fr.kompass.com/r/ile-de-france/fr_11/", "url_link": "", "url-href": "https://www.fiparc.fr/"},{"web-scraper-order": "1638891898-601", "web-scraper-start-url": "https://fr.kompass.com/r/ile-de-france/fr_11/", "url_link": "", "url-href": "https://www.u-pec.fr/"},{"web-scraper-order": "1638891898-610", "web-scraper-start-url": "https://fr.kompass.com/r/ile-de-france/fr_11/", "url_link": "", "url-href": "https://www.manandmachine.fr/"},{"web-scraper-order": "1638891898-583", "web-scraper-start-url": "https://fr.kompass.com/r/ile-de-france/fr_11/", "url_link": "", "url-href": "https://www.options.fr/"},{"web-scraper-order": "1638891898-588", "web-scraper-start-url": "https://fr.kompass.com/r/ile-de-france/fr_11/", "url_link": "", "url-href": "https://www.ecmu-csr.com/"},{"web-scraper-order": "1638891898-625", "web-scraper-start-url": "https://fr.kompass.com/r/ile-de-france/fr_11/", "url_link": "", "url-href": "https://www.uddeholm.com/france/fr/"},{"web-scraper-order": "1638891898-574", "web-scraper-start-url": "https://fr.kompass.com/r/ile-de-france/fr_11/", "url_link": "", "url-href": "https://pomona.fr/"},{"web-scraper-order": "1638891898-561", "web-scraper-start-url": "https://fr.kompass.com/r/ile-de-france/fr_11/", "url_link": "", "url-href": "https://nusconsulting.com/"},{"web-scraper-order": "1638891898-614", "web-scraper-start-url": "https://fr.kompass.com/r/ile-de-france/fr_11/", "url_link": "", "url-href": "https://flashtransports.fr/"},{"web-scraper-order": "1638891898-565", "web-scraper-start-url": "https://fr.kompass.com/r/ile-de-france/fr_11/", "url_link": "", "url-href": "https://sifalogistics.com/"},{"web-scraper-order": "1638891898-620", "web-scraper-start-url": "https://fr.kompass.com/r/ile-de-france/fr_11/", "url_link": "", "url-href": "https://www.itelis.fr/"},{"web-scraper-order": "1638891898-633", "web-scraper-start-url": "https://fr.kompass.com/r/ile-de-france/fr_11/", "url_link": "", "url-href": "https://www.ifpenergiesnouvelles.fr/"},{"web-scraper-order": "1638891898-569", "web-scraper-start-url": "https://fr.kompass.com/r/ile-de-france/fr_11/", "url_link": "", "url-href": "https://www.prym-fashion.com/"},{"web-scraper-order": "1638891898-628", "web-scraper-start-url": "https://fr.kompass.com/r/ile-de-france/fr_11/", "url_link": "", "url-href": "https://europehydro.com/"},{"web-scraper-order": "1638891898-589", "web-scraper-start-url": "https://fr.kompass.com/r/ile-de-france/fr_11/", "url_link": "", "url-href": "https://www.comiteo.net/"},{"web-scraper-order": "1638891898-563", "web-scraper-start-url": "https://fr.kompass.com/r/ile-de-france/fr_11/", "url_link": "", "url-href": "https://www.ecofluide.com/fr/"},{"web-scraper-order": "1638891898-562", "web-scraper-start-url": "https://fr.kompass.com/r/ile-de-france/fr_11/", "url_link": "", "url-href": "https://ateq.com/"},{"web-scraper-order": "1638891898-593", "web-scraper-start-url": "https://fr.kompass.com/r/ile-de-france/fr_11/", "url_link": "", "url-href": "https://licornefinance.com/"}
]